igenius_adapters_sdk/__init__.py
igenius_adapters_sdk/entities/__init__.py
igenius_adapters_sdk/entities/attribute.py
igenius_adapters_sdk/entities/collection.py
igenius_adapters_sdk/entities/data.py
igenius_adapters_sdk/entities/errors.py
igenius_adapters_sdk/entities/i18n.py
igenius_adapters_sdk/entities/numeric_binning.py
igenius_adapters_sdk/entities/params.py
igenius_adapters_sdk/entities/query.py
igenius_adapters_sdk/entities/uri.py
igenius_adapters_sdk/tools/__init__.py
igenius_adapters_sdk/tools/chassis.py
igenius_adapters_sdk/tools/utils.py
igenius_adapters_sdk-4.0.0.dist-info/LICENSE
igenius_adapters_sdk-4.0.0.dist-info/WHEEL
igenius_adapters_sdk-4.0.0.dist-info/METADATA
igenius_adapters_sdk-4.0.0.dist-info/RECORD
