Metadata-Version: 2.1
Name: igenius-adapters-sdk
Version: 4.0.0
Summary: The iGenius Software Development Kit to develop crystal datasource adapters.
Home-page: https://github.com/iGenius-Srl/igenius-adapters-sdk
Author: iGenius Backend
Author-email: backend@igenius.ai
Requires-Python: >=3.8.1,<4.0.0
Classifier: Programming Language :: Python :: 3
Classifier: Topic :: Software Development :: Libraries
Classifier: Topic :: Software Development :: Libraries :: Application Frameworks
Requires-Dist: pydantic (>=2.1.0,<3.0.0)
Requires-Dist: typing-extensions (>=4.0.0,<5.0.0)
